CHANGES.rst
DESCRIPTION.rst
LICENSE
MANIFEST.in
README.md
setup.py
src/wai.annotations.bluechannel.egg-info/PKG-INFO
src/wai.annotations.bluechannel.egg-info/SOURCES.txt
src/wai.annotations.bluechannel.egg-info/dependency_links.txt
src/wai.annotations.bluechannel.egg-info/entry_points.txt
src/wai.annotations.bluechannel.egg-info/namespace_packages.txt
src/wai.annotations.bluechannel.egg-info/requires.txt
src/wai.annotations.bluechannel.egg-info/top_level.txt
src/wai/annotations/blue_channel/__init__.py
src/wai/annotations/blue_channel/component/_BlueChannelReader.py
src/wai/annotations/blue_channel/component/_BlueChannelWriter.py
src/wai/annotations/blue_channel/component/_FromBlueChannel.py
src/wai/annotations/blue_channel/component/_ToBlueChannel.py
src/wai/annotations/blue_channel/component/__init__.py
src/wai/annotations/blue_channel/specifier/_BlueChannelInputFormatSpecifier.py
src/wai/annotations/blue_channel/specifier/_BlueChannelOutputFormatSpecifier.py
src/wai/annotations/blue_channel/specifier/__init__.py
src/wai/annotations/blue_channel/util/__init__.py
src/wai/annotations/blue_channel/util/_format.py